{
  "project_info": {
    "project_number": "208528899209",
    "project_id": "projetflutter-9d67f",
    "storage_bucket": "projetflutter-9d67f.appspot.com"
  },
  "client": [
    {
      "client_info": {
        "mobilesdk_app_id": "1:208528899209:android:c529475e4dde06daf7da58",
        "android_client_info": {
          "package_name": "com.example.flutter_app"
        }
      },
      "oauth_client": [
        {
          "client_id": "208528899209-5bv8oukukqhhjr5coslvpebq7ps3k2p7.apps.googleusercontent.com",
          "client_type": 1,
          "android_info": {
            "package_name": "com.example.flutter_app",
            "certificate_hash": "6a2a0aebaa01ca52654ce9a7ed925de905d4077b"
          }
        },
        {
          "client_id": "208528899209-0imkt0f4eo2v281uujfsae7gp50sjv5o.apps.googleusercontent.com",
          "client_type": 3
        }
      ],
      "api_key": [
        {
          "current_key": "AIzaSyCSfLhfRaIltskP-VttoQPvo8Qdlt17vsE"
        }
      ],
      "services": {
        "appinvite_service": {
          "other_platform_oauth_client": [
            {
              "client_id": "208528899209-0imkt0f4eo2v281uujfsae7gp50sjv5o.apps.googleusercontent.com",
              "client_type": 3
            }
          ]
        }
      }
    }
  ],
  "configuration_version": "1"
}